agentserve/__init__.py
agentserve/agent_registry.py
agentserve/agent_server.py
agentserve/cli.py
agentserve/config.py
agentserve/logging_config.py
agentserve/queues/calery_task_queue.py
agentserve/queues/local_task_queue.py
agentserve/queues/redis_task_queue.py
agentserve/queues/task_queue.py
agentserve-0.2.10.dist-info/LICENSE
agentserve-0.2.10.dist-info/METADATA
agentserve-0.2.10.dist-info/WHEEL
agentserve-0.2.10.dist-info/entry_points.txt
agentserve-0.2.10.dist-info/top_level.txt
agentserve-0.2.10.dist-info/RECORD
