Metadata-Version: 2.1
Name: agentserve
Version: 0.2.10
Summary: A framework for hosting and scaling AI agents.
Home-page: https://github.com/PropsAI/agentserve
Author: Peter
Author-email: peter@getprops.ai
Classifier: Programming Language :: Python :: 3
Classifier: License :: OSI Approved :: MIT License
License-File: LICENSE
Requires-Dist: fastapi
Requires-Dist: uvicorn
Requires-Dist: rq
Requires-Dist: redis
Requires-Dist: celery
Requires-Dist: click
Requires-Dist: pydantic
Requires-Dist: pyyaml
